MANIFEST.in
setup.py
bin/jtalks
jtalks/ApplicationContext.py
jtalks/DB.py
jtalks/DeployCommand.py
jtalks/Main.py
jtalks/Nexus.py
jtalks/OldNexus.py
jtalks/ScriptSettings.py
jtalks/Tomcat.py
jtalks/__init__.py
jtalks/backup/Backuper.py
jtalks/backup/__init__.py
jtalks/db/DbOperations.py
jtalks/db/__init__.py
jtalks/parser/PomFile.py
jtalks/parser/WrongConfigException.py
jtalks/parser/__init__.py
jtalks/sanity/SanityCheckFailedException.py
jtalks/sanity/SanityTest.py
jtalks/sanity/__init__.py
jtalks/util/EnvList.py
jtalks/util/EnvironmentConfigGrabber.py
jtalks/util/LibVersion.py
jtalks/util/Logger.py
jtalks/util/__init__.py
jtalks_cicd.egg-info/PKG-INFO
jtalks_cicd.egg-info/SOURCES.txt
jtalks_cicd.egg-info/dependency_links.txt
jtalks_cicd.egg-info/not-zip-safe
jtalks_cicd.egg-info/requires.txt
jtalks_cicd.egg-info/top_level.txt
tests/ApplicationContextTest.py
tests/DeployCommandTest.py
tests/EnvListTest.py
tests/NexusTest.py
tests/OldNexusTest.py
tests/ScriptSettingsTest.py
tests/TomcatTest.py
tests/__init__.py
tests/backup/BackuperTest.py
tests/backup/__init__.py