Metadata-Version: 1.0
Name: jtalks-cicd
Version: 2.0.14
Summary: Installs JTalks apps like jcommune and poulpe configuring them. Usually used by CI to implement CD (continuous delivery)
Home-page: http://github.com/jtalks-org/jtalks-cicd
Author: Stanislav Bashkyrtsev
Author-email: stanislav.bashkirtsev@gmail.com
License: UNKNOWN
Platform: UNKNOWN
